LICENSE
README.md
setup.py
src/flask_reactize/__init__.py
src/flask_reactize/flask_reactize.py
src/flask_reactize/node_wrapper.py
src/flask_reactize/utils.py
src/flask_reactize.egg-info/PKG-INFO
src/flask_reactize.egg-info/SOURCES.txt
src/flask_reactize.egg-info/dependency_links.txt
src/flask_reactize.egg-info/requires.txt
src/flask_reactize.egg-info/top_level.txt