Metadata-Version: 2.1
Name: flask-reactize
Version: 1.0.0a3
Summary: Serve React JS application from a Flask application.
Home-page: https://github.com/jchomarat/flask-reactize
Author: Julien Chomarat
Author-email: julien.chomarat@gmail.com
License: MIT
Project-URL: Bug Tracker, https://github.com/jchomarat/flask-reactize/issues
Keywords: python
Platform: UNKNOWN
Classifier: Development Status :: 3 - Alpha
Classifier: Programming Language :: Python :: 3.8
Classifier: Programming Language :: Python :: 3.10
Requires-Python: >=3.8
License-File: LICENSE
